tpu_info/__init__.py
tpu_info/args.py
tpu_info/args_helper.py
tpu_info/cli.py
tpu_info/cli_helper.py
tpu_info/device.py
tpu_info/metrics.py
tpu_info/proto/__init__.py
tpu_info/proto/tpu_metric_service_pb2.py
tpu_info/proto/tpu_metric_service_pb2.pyi
tpu_info/proto/tpu_metric_service_pb2_grpc.py
tpu_info/proto/tpu_telemetry_pb2.py
tpu_info/proto/tpu_telemetry_pb2.pyi
tpu_info-0.8.1.dist-info/METADATA
tpu_info-0.8.1.dist-info/WHEEL
tpu_info-0.8.1.dist-info/entry_points.txt
tpu_info-0.8.1.dist-info/RECORD
