Metadata-Version: 2.4
Name: tpu-info
Version: 0.8.1
Summary: CLI tool to view TPU metrics
Project-URL: homepage, https://github.com/google/cloud-accelerator-diagnostics/tree/main/tpu_info
Project-URL: repository, https://github.com/google/cloud-accelerator-diagnostics
Author-email: Cloud TPU Team <cloud-tpu-eng@google.com>
License: Apache-2.0
Requires-Python: >=3.8
Requires-Dist: grpcio>=1.65.5
Requires-Dist: packaging
Requires-Dist: protobuf
Requires-Dist: rich
Provides-Extra: test
Requires-Dist: absl-py; extra == 'test'
